{"_notifyingListeners":false,"_scopeListeners":[],"_eventProcessors":[],"_breadcrumbs":[{"timestamp":1694818734.311,"category":"console","data":{"arguments":["Initializing krisp module"],"logger":"console"},"level":"info","message":"Initializing krisp module"},{"timestamp":1694818734.799,"category":"console","level":"log","message":"mainScreen.UpdaterEvents: UPDATER_HISTORY_QUERY_AND_TRUNCATE"},{"timestamp":1694818734.813,"category":"console","level":"log","message":"mainScreen.UpdaterEvents: UPDATER_HISTORY_QUERY_AND_TRUNCATE"},{"timestamp":1694818735.765,"category":"console","level":"log","message":"mainScreen.UpdaterEvents: CHECK_FOR_UPDATES UPDATE_NOT_AVAILABLE"},{"timestamp":1694818735.765,"category":"console","level":"log","message":"2023-09-15T22:58:55.765Z [Modules] Checking for host updates."},{"timestamp":1694818735.895,"type":"http","category":"electron.net","data":{"url":"https://discord.com/api/updates/canary?platform=linux&version=0.0.167","method":"GET","status_code":204}},{"timestamp":1694818735.897,"category":"console","level":"log","message":"2023-09-15T22:58:55.897Z [Modules] Host is up to date."},{"timestamp":1694818735.897,"category":"console","level":"log","message":"2023-09-15T22:58:55.897Z [Modules] Checking for module updates at https://discord.com/api/modules/canary/versions.json"},{"timestamp":1694818735.9,"type":"http","category":"electron.net","data":{"url":"https://discord.com/api/modules/canary/versions.json?host_version=0.0.167&platform=linux&_=5649395","method":"GET","status_code":200}},{"timestamp":1694818735.9,"category":"console","level":"log","message":"2023-09-15T22:58:55.900Z [Modules] No module updates available."},{"timestamp":1694818735.901,"category":"console","level":"log","message":"legacyModuleUpdater: update-check-finished"},{"timestamp":1694818736.187,"category":"console","level":"log","message":"legacyModuleUpdater: installed-module discord_rpc 1 1 true"},{"timestamp":1694818736.208,"category":"console","level":"log","message":"mainScreen.on(did-finish-load) false false"},{"timestamp":1694818736.209,"category":"console","level":"log","message":"splashScreen.pageReady"},{"timestamp":1694818736.21,"category":"electron","message":"window.show","type":"ui","data":{"id":2,"url":"https://canary.discord.com/app?_=1694818732350","title":""}},{"timestamp":1694818736.21,"category":"console","level":"log","message":"blackbox: 2023-09-15T22:58:56.210Z 9 ✅ webContents.did-finish-load web2"},{"timestamp":1694818736.241,"category":"electron","message":"window.blur","type":"ui","data":{"id":1,"url":"app:///app_bootstrap/splash/index.html"}},{"timestamp":1694818736.242,"category":"electron","message":"app.browser-window-blur","type":"ui"},{"timestamp":1694818736.242,"category":"electron","message":"window.focus","type":"ui","data":{"id":2,"url":"https://canary.discord.com/app?_=1694818732350","title":""}},{"timestamp":1694818736.242,"category":"electron","message":"app.browser-window-focus","type":"ui"},{"timestamp":1694818736.309,"category":"electron","message":"window.hide","type":"ui","data":{"id":1,"url":"app:///app_bootstrap/splash/index.html"}},{"timestamp":1694818736.309,"category":"electron","message":"window.close","type":"ui","data":{"id":1,"url":"app:///app_bootstrap/splash/index.html"}},{"timestamp":1694818736.31,"category":"console","level":"log","message":"blackbox: 2023-09-15T22:58:56.310Z 10 window.close win1"},{"timestamp":1694818736.319,"category":"electron","message":"renderer.destroyed","type":"ui","data":{"id":1,"url":"app:///app_bootstrap/splash/index.html"}},{"timestamp":1694818736.417,"category":"electron","message":"window.closed","type":"ui","data":{"id":1,"url":"app:///app_bootstrap/splash/index.html"}},{"timestamp":1694818736.42,"category":"console","level":"log","message":"mainScreen.UpdaterEvents: UPDATER_HISTORY_QUERY_AND_TRUNCATE"},{"timestamp":1694818736.423,"category":"console","level":"log","message":"blackbox: 2023-09-15T22:58:56.423Z 11 webContents.destroyed web1"},{"timestamp":1694818736.425,"category":"console","level":"log","message":"blackbox: 2023-09-15T22:58:56.425Z 12 window.closed win1"},{"timestamp":1694818741.066,"category":"ui.click","message":"button.button-12Fmur.enabled-9OeuTA.button-ejjZWC.lookBlank-FgPMy6.colorBrand-2M3O3N.grow-2T4nbg.button-12Fmur[aria-label=\"Rendre muet\"][type=\"button\"]"},{"timestamp":1694818745.238,"category":"ui.click","message":"foreignobject > div.wrapper-3kah-n.selected-1Drb7Z[aria-label=\" Team Smoothie\"]"},{"timestamp":1694818750.14,"category":"ui.click","message":"div.contents-3NembX > svg"},{"timestamp":1694818751.752,"category":"ui.click","message":"div.item-2GWPIy.selected-1sf9UK.themed-qqoYp3"},{"timestamp":1694818752.905,"category":"ui.click","message":"div.flexChild-3PzYmX > div.select-Zz0IcO.open-LeyjhI.lookFilled-GPyucw"},{"timestamp":1694818753.664,"category":"ui.click","message":"div.select-Zz0IcO.open-LeyjhI.lookFilled-GPyucw > span.value-2en4z7"},{"timestamp":1694818755.374,"category":"ui.click","message":"div.contentRegionScroller-2_GT_N.contentRegionShownSidebar-fHXkEg.auto-2TJ1RH.scrollerBase-1Pkza4"},{"timestamp":1694818758.571,"category":"electron","message":"window.blur","type":"ui","data":{"id":2,"url":"https://canary.discord.com/channels/591402447734439939/699750192588783617"}},{"timestamp":1694818758.572,"category":"electron","message":"app.browser-window-blur","type":"ui"},{"timestamp":1694818774.117,"category":"electron","message":"window.focus","type":"ui","data":{"id":2,"url":"https://canary.discord.com/channels/591402447734439939/699750192588783617"}},{"timestamp":1694818774.117,"category":"electron","message":"app.browser-window-focus","type":"ui"},{"timestamp":1694818774.137,"category":"electron","message":"window.blur","type":"ui","data":{"id":2,"url":"https://canary.discord.com/channels/591402447734439939/699750192588783617"}},{"timestamp":1694818774.137,"category":"electron","message":"app.browser-window-blur","type":"ui"},{"timestamp":1694818775.618,"category":"electron","message":"window.focus","type":"ui","data":{"id":2,"url":"https://canary.discord.com/channels/591402447734439939/699750192588783617"}},{"timestamp":1694818775.618,"category":"electron","message":"app.browser-window-focus","type":"ui"},{"timestamp":1694818787.272,"category":"electron","message":"window.blur","type":"ui","data":{"id":2,"url":"https://canary.discord.com/channels/591402447734439939/699750192588783617"}},{"timestamp":1694818787.272,"category":"electron","message":"app.browser-window-blur","type":"ui"},{"timestamp":1694818789.218,"category":"electron","message":"window.focus","type":"ui","data":{"id":2,"url":"https://canary.discord.com/channels/591402447734439939/699750192588783617"}},{"timestamp":1694818789.218,"category":"electron","message":"app.browser-window-focus","type":"ui"},{"timestamp":1694818789.32,"category":"electron","message":"window.blur","type":"ui","data":{"id":2,"url":"https://canary.discord.com/channels/591402447734439939/699750192588783617"}},{"timestamp":1694818789.32,"category":"electron","message":"app.browser-window-blur","type":"ui"},{"timestamp":1694818811.803,"category":"electron","message":"window.focus","type":"ui","data":{"id":2,"url":"https://canary.discord.com/channels/591402447734439939/699750192588783617"}},{"timestamp":1694818811.803,"category":"electron","message":"app.browser-window-focus","type":"ui"},{"timestamp":1694818811.817,"category":"electron","message":"window.blur","type":"ui","data":{"id":2,"url":"https://canary.discord.com/channels/591402447734439939/699750192588783617"}},{"timestamp":1694818811.817,"category":"electron","message":"app.browser-window-blur","type":"ui"},{"timestamp":1694818811.833,"category":"electron","message":"window.focus","type":"ui","data":{"id":2,"url":"https://canary.discord.com/channels/591402447734439939/699750192588783617"}},{"timestamp":1694818811.833,"category":"electron","message":"app.browser-window-focus","type":"ui"},{"timestamp":1694818811.968,"category":"ui.click","message":"button.micTestButton-2ga9tS.button-ejjZWC.lookFilled-1H2Jvj.colorBrand-2M3O3N.sizeSmall-3R2P2p[type=\"button\"]"},{"timestamp":1694818812.737,"category":"ui.click","message":"div.contents-3NembX"},{"timestamp":1694818816.384,"category":"ui.click","message":"div.contents-3NembX"},{"timestamp":1694818820.43,"category":"electron","message":"window.blur","type":"ui","data":{"id":2,"url":"https://canary.discord.com/channels/591402447734439939/699750192588783617"}},{"timestamp":1694818820.43,"category":"electron","message":"app.browser-window-blur","type":"ui"},{"timestamp":1694818823.223,"category":"electron","message":"window.focus","type":"ui","data":{"id":2,"url":"https://canary.discord.com/channels/591402447734439939/699750192588783617"}},{"timestamp":1694818823.223,"category":"electron","message":"app.browser-window-focus","type":"ui"},{"timestamp":1694818823.233,"category":"electron","message":"window.blur","type":"ui","data":{"id":2,"url":"https://canary.discord.com/channels/591402447734439939/699750192588783617"}},{"timestamp":1694818823.233,"category":"electron","message":"app.browser-window-blur","type":"ui"},{"timestamp":1694818823.249,"category":"electron","message":"window.focus","type":"ui","data":{"id":2,"url":"https://canary.discord.com/channels/591402447734439939/699750192588783617"}},{"timestamp":1694818823.249,"category":"electron","message":"app.browser-window-focus","type":"ui"},{"timestamp":1694818823.394,"category":"ui.click","message":"div.contents-3NembX"},{"timestamp":1694818826.551,"category":"electron","message":"window.blur","type":"ui","data":{"id":2,"url":"https://canary.discord.com/channels/591402447734439939/699750192588783617"}},{"timestamp":1694818826.551,"category":"electron","message":"app.browser-window-blur","type":"ui"},{"timestamp":1694818840.293,"category":"electron","message":"window.focus","type":"ui","data":{"id":2,"url":"https://canary.discord.com/channels/591402447734439939/699750192588783617"}},{"timestamp":1694818840.293,"category":"electron","message":"app.browser-window-focus","type":"ui"},{"timestamp":1694818840.294,"category":"electron","message":"window.blur","type":"ui","data":{"id":2,"url":"https://canary.discord.com/channels/591402447734439939/699750192588783617"}},{"timestamp":1694818840.294,"category":"electron","message":"app.browser-window-blur","type":"ui"},{"timestamp":1694818840.294,"category":"electron","message":"window.focus","type":"ui","data":{"id":2,"url":"https://canary.discord.com/channels/591402447734439939/699750192588783617"}},{"timestamp":1694818840.294,"category":"electron","message":"app.browser-window-focus","type":"ui"},{"timestamp":1694818840.439,"category":"ui.click","message":"div.micTest-19EtdQ > div.wrapper-UvA17F > div.container-3NTP7o > svg > rect"},{"timestamp":1694818841.359,"category":"electron","message":"window.close","type":"ui","data":{"id":2,"url":"https://canary.discord.com/channels/591402447734439939/699750192588783617"}},{"timestamp":1694818841.36,"category":"electron","message":"window.hide","type":"ui","data":{"id":2,"url":"https://canary.discord.com/channels/591402447734439939/699750192588783617"}},{"timestamp":1694818841.36,"category":"console","level":"log","message":"blackbox: 2023-09-15T23:00:41.360Z 13 window.close win2"},{"timestamp":1694818841.365,"category":"electron","message":"window.blur","type":"ui","data":{"id":2,"url":"https://canary.discord.com/channels/591402447734439939/699750192588783617"}},{"timestamp":1694818841.365,"category":"electron","message":"app.browser-window-blur","type":"ui"},{"timestamp":1694818847.356,"category":"electron","message":"app.second-instance","type":"ui"},{"timestamp":1694818847.358,"category":"electron","message":"window.show","type":"ui","data":{"id":2,"url":"https://canary.discord.com/channels/591402447734439939/699750192588783617"}},{"timestamp":1694818847.36,"category":"electron","message":"window.show","type":"ui","data":{"id":2,"url":"https://canary.discord.com/channels/591402447734439939/699750192588783617"}},{"timestamp":1694818847.361,"category":"electron","message":"window.focus","type":"ui","data":{"id":2,"url":"https://canary.discord.com/channels/591402447734439939/699750192588783617"}},{"timestamp":1694818847.361,"category":"electron","message":"app.browser-window-focus","type":"ui"},{"timestamp":1694819434.514,"category":"ui.click","message":"div.select-Zz0IcO.open-LeyjhI.lookFilled-GPyucw > span.value-2en4z7"},{"timestamp":1694819435.486,"category":"ui.click","message":"div.flexChild-3PzYmX > div.select-Zz0IcO.open-LeyjhI.lookFilled-GPyucw"},{"timestamp":1694819436.693,"category":"ui.click","message":"div.container-O54IuJ > div.closeButton-PCZcma[aria-label=\"Fermer\"] > svg"},{"timestamp":1694819439.708,"category":"ui.click","message":"button.button-12Fmur.enabled-9OeuTA.button-ejjZWC.lookBlank-FgPMy6.colorBrand-2M3O3N.grow-2T4nbg.button-12Fmur[aria-label=\"Mettre en sourdine\"][type=\"button\"]"},{"timestamp":1694819440.052,"category":"ui.click","message":"div.contents-3NembX > svg"},{"timestamp":1694819441.016,"category":"ui.click","message":"svg > path"},{"timestamp":1694819442.442,"category":"ui.click","message":"div.closeButton-30b1gR[aria-label=\"Ignorer\"]"},{"timestamp":1694819442.912,"category":"ui.click","message":"div.container-1eFtFS > div.base-2jDfDU > div.notice-2HEN-u.colorDanger-2YLzLC"},{"timestamp":1694819443.358,"category":"ui.click","message":"div#message-accessories-1151256220473249792.container-2sjPya"},{"timestamp":1694819443.605,"category":"electron","message":"window.close","type":"ui","data":{"id":2,"url":"https://canary.discord.com/channels/591402447734439939/699750192588783617"}},{"timestamp":1694819443.606,"category":"electron","message":"window.hide","type":"ui","data":{"id":2,"url":"https://canary.discord.com/channels/591402447734439939/699750192588783617"}},{"timestamp":1694819443.606,"category":"console","level":"log","message":"blackbox: 2023-09-15T23:10:43.606Z 14 window.close win2"},{"timestamp":1694819443.613,"category":"electron","message":"window.blur","type":"ui","data":{"id":2,"url":"https://canary.discord.com/channels/591402447734439939/699750192588783617"}},{"timestamp":1694819443.613,"category":"electron","message":"app.browser-window-blur","type":"ui"}],"_attachments":[],"_user":{"id":"909413292433354763","username":"barnabait","email":"barnabaitpro@gmail.com"},"_tags":{"nativeBuildNumber":"null"},"_extra":{},"_contexts":{},"_sdkProcessingMetadata":{}}